laserhammer/__init__.py
laserhammer-2.4.data/scripts/laserhammer
laserhammer-2.4.dist-info/METADATA
laserhammer-2.4.dist-info/RECORD
laserhammer-2.4.dist-info/WHEEL
laserhammer-2.4.dist-info/top_level.txt
