Metadata-Version: 2.1
Name: laserhammer
Version: 2.4
Summary: DocBook to mdoc(7) converter
Home-page: https://github.com/trasz/laserhammer
Author: Edward Tomasz Napierała
Author-email: trasz@FreeBSD.org
License: UNKNOWN
Platform: UNKNOWN
Classifier: Programming Language :: Python :: 3
Classifier: License :: OSI Approved :: BSD License
Classifier: Operating System :: OS Independent
Classifier: Topic :: Text Processing :: Markup :: XML
Classifier: Topic :: Utilities
